<?xml version="1.0" encoding="utf-8" ?>
<app>
	<stack style="main">

		<hbox style="fullWidth">

			<vbox>

				<vbox style="summaryContainer">
					<userSummary style="summaryView" />
				</vbox>

				<titleContainer style="summaryContainer" title="Videos">
					<videosSummary style="summaryView" />
				</titleContainer>

				<!-- <titleContainer style="summaryContainer" title="Likes &amp; Follows">
					<activitySummary style="summaryView" />
				</titleContainer> -->

			</vbox>

			<vbox style="moogaloop">
				<moogaloop style="fullWidth" />
			</vbox>

		</hbox>

	</stack>
</app>